Workbook

Sheet Resumen
A1: Resumen de ganancias de clipping
A2: Estimaciones, no garantías: los resultados reales dependen de tus vistas, campañas y clientes.
A4: Ganancia neta del año (MXN) | B4: ='Proyección 12 meses'!O17 -> 227136.77
A5: Ganancia neta promedio al mes (MXN) | B5: ='Proyección 12 meses'!O17/12 -> 18928.064
A6: Ganancia neta del mes 1 (MXN) | B6: ='Proyección 12 meses'!O5 -> 3421.372
A7: Ganancia neta del mes 12 (MXN) | B7: ='Proyección 12 meses'!O16 -> 35708.32
A8: Clips subidos en el año | B8: ='Proyección 12 meses'!B17 -> 1248
A9: Vistas totales en el año | B9: ='Proyección 12 meses'!D17 -> 9048520.2
A10: Parte de la ganancia bruta que viene de clientes fijos | B10: =IFERROR('Proyección 12 meses'!J17/'Proyección 12 meses'!K17,0) -> 0.49663487
A12: Cómo usar esta hoja
A13: 1. Ve a la pestaña 'Supuestos' y cambia los valores azules con fondo amarillo.
A14: 2. En 'Proyección 12 meses', ajusta cuántos clientes fijos tienes cada mes.
A15: 3. Cada mes, reemplaza las estimaciones por tus vistas y pagos reales para mejorar la proyección.
A16: Colores: azul = datos que tú cambias · negro = fórmulas · verde = datos traídos de otra pestaña.

Sheet Supuestos
A1: Ganancias de clipping — supuestos
A2: Cambia solo las celdas con texto AZUL y fondo AMARILLO. Todo lo demás se calcula solo.
A4: PRODUCCIÓN
A5: Clips subidos por día | B5: 4 | C5: Recomendación para empezar: 3 a 5 clips diarios.
A6: Días que subes por semana | B6: 6
A7: Vistas promedio por clip en el mes 1 | B7: 3000 | C7: Estimación para una cuenta nueva. Revísalo con tus números reales cada mes.
A8: Crecimiento mensual de vistas por clip | B8: 0.15 | C8: Cuánto mejoran tus vistas promedio cada mes al aprender qué funciona. Estimación.
A9: CAMPAÑAS DE CLIPPING
A10: % de clips que suben a campañas pagadas | B10: 0.7 | C10: El resto de clips se suben a tu propio canal (Shorts).
A11: Pago por cada 1,000 vistas (USD) | B11: 1 | C11: Rango común en campañas: 0.50 a 3 USD por 1,000 vistas. Varía por campaña.
A12: Tope mensual de pago por campañas (USD) | B12: 1500 | C12: Las campañas tienen presupuesto limitado; esto evita proyecciones irreales.
A13: YOUTUBE SHORTS
A14: Pago de Shorts por cada 1,000 vistas (USD) | B14: 0.03 | C14: Estimación para público de México/español: aprox. 0.01 a 0.05 USD por 1,000 vistas.
A15: Mes en que empiezas a monetizar Shorts | B15: 5 | C15: YouTube pide 1,000 suscriptores y 10 millones de vistas de Shorts en 90 días.
A16: CLIENTES FIJOS (editor de clips)
A17: Cuota mensual por cliente (MXN) | B17: 6000 | C17: Rango común con creadores mexicanos: 3,000 a 15,000 MXN al mes.
A18: DINERO Y GASTOS
A19: Tipo de cambio (MXN por USD) | B19: 19 | C19: Aproximado. Actualízalo con el tipo de cambio del día.
A20: Comisión por recibir dólares (PayPal/Wise) | B20: 0.04 | C20: Estimación de comisión + conversión. Revisa la de tu servicio.
A21: Impuesto (ISR RESICO aprox.) | B21: 0.015 | C21: RESICO para personas físicas: aprox. 1% a 2.5% según ingresos. Confírmalo con un contador.
A22: Gastos mensuales (internet, apps, etc., MXN) | B22: 500

Sheet Proyección 12 meses
A1: Proyección de ganancias de clipping — 12 meses
A2: La columna 'Clientes fijos' (azul/amarillo) también la puedes cambiar: es cuántos creadores te pagan cuota ese mes.
A4: Mes | B4: Clips subidos | C4: Vistas promedio por clip | D4: Vistas totales | E4: Ingreso campañas (USD) | F4: Ingreso Shorts (USD) | G4: Ingreso en dólares (USD) | H4: Ingreso en dólares (MXN) | I4: Clientes fijos | J4: Ingreso clientes (MXN) | K4: Ingreso bruto (MXN) | L4: Comisiones (MXN) | M4: Impuestos (MXN) | N4: Gastos (MXN) | O4: Ganancia neta (MXN)
A5: 1 | B5: =ROUND(Supuestos!$B$5*Supuestos!$B$6*52/12,0) -> 104 | C5: =Supuestos!$B$7*(1+Supuestos!$B$8)^(A5-1) -> 3000 | D5: =B5*C5 -> 312000 | E5: =MIN(D5*Supuestos!$B$10/1000*Supuestos!$B$11,Supuestos!$B$12) -> 218.4 | F5: =IF(A5>=Supuestos!$B$15,D5*(1-Supuestos!$B$10)/1000*Supuestos!$B$14,0) -> 0 | G5: =E5+F5 -> 218.4 | H5: =G5*Supuestos!$B$19 -> 4149.6 | I5: 0 | J5: =I5*Supuestos!$B$17 -> 0 | K5: =H5+J5 -> 4149.6 | L5: =H5*Supuestos!$B$20 -> 165.984 | M5: =K5*Supuestos!$B$21 -> 62.244 | N5: =Supuestos!$B$22 -> 500 | O5: =K5-L5-M5-N5 -> 3421.372
A6: 2 | B6: =ROUND(Supuestos!$B$5*Supuestos!$B$6*52/12,0) -> 104 | C6: =Supuestos!$B$7*(1+Supuestos!$B$8)^(A6-1) -> 3450 | D6: =B6*C6 -> 358800 | E6: =MIN(D6*Supuestos!$B$10/1000*Supuestos!$B$11,Supuestos!$B$12) -> 251.16 | F6: =IF(A6>=Supuestos!$B$15,D6*(1-Supuestos!$B$10)/1000*Supuestos!$B$14,0) -> 0 | G6: =E6+F6 -> 251.16 | H6: =G6*Supuestos!$B$19 -> 4772.04 | I6: 0 | J6: =I6*Supuestos!$B$17 -> 0 | K6: =H6+J6 -> 4772.04 | L6: =H6*Supuestos!$B$20 -> 190.8816 | M6: =K6*Supuestos!$B$21 -> 71.5806 | N6: =Supuestos!$B$22 -> 500 | O6: =K6-L6-M6-N6 -> 4009.5778
A7: 3 | B7: =ROUND(Supuestos!$B$5*Supuestos!$B$6*52/12,0) -> 104 | C7: =Supuestos!$B$7*(1+Supuestos!$B$8)^(A7-1) -> 3967.5 | D7: =B7*C7 -> 412620 | E7: =MIN(D7*Supuestos!$B$10/1000*Supuestos!$B$11,Supuestos!$B$12) -> 288.834 | F7: =IF(A7>=Supuestos!$B$15,D7*(1-Supuestos!$B$10)/1000*Supuestos!$B$14,0) -> 0 | G7: =E7+F7 -> 288.834 | H7: =G7*Supuestos!$B$19 -> 5487.846 | I7: 1 | J7: =I7*Supuestos!$B$17 -> 6000 | K7: =H7+J7 -> 11487.846 | L7: =H7*Supuestos!$B$20 -> 219.51384 | M7: =K7*Supuestos!$B$21 -> 172.31769 | N7: =Supuestos!$B$22 -> 500 | O7: =K7-L7-M7-N7 -> 10596.014
A8: 4 | B8: =ROUND(Supuestos!$B$5*Supuestos!$B$6*52/12,0) -> 104 | C8: =Supuestos!$B$7*(1+Supuestos!$B$8)^(A8-1) -> 4562.625 | D8: =B8*C8 -> 474513 | E8: =MIN(D8*Supuestos!$B$10/1000*Supuestos!$B$11,Supuestos!$B$12) -> 332.1591 | F8: =IF(A8>=Supuestos!$B$15,D8*(1-Supuestos!$B$10)/1000*Supuestos!$B$14,0) -> 0 | G8: =E8+F8 -> 332.1591 | H8: =G8*Supuestos!$B$19 -> 6311.0229 | I8: 1 | J8: =I8*Supuestos!$B$17 -> 6000 | K8: =H8+J8 -> 12311.023 | L8: =H8*Supuestos!$B$20 -> 252.44092 | M8: =K8*Supuestos!$B$21 -> 184.66534 | N8: =Supuestos!$B$22 -> 500 | O8: =K8-L8-M8-N8 -> 11373.917
A9: 5 | B9: =ROUND(Supuestos!$B$5*Supuestos!$B$6*52/12,0) -> 104 | C9: =Supuestos!$B$7*(1+Supuestos!$B$8)^(A9-1) -> 5247.0188 | D9: =B9*C9 -> 545689.95 | E9: =MIN(D9*Supuestos!$B$10/1000*Supuestos!$B$11,Supuestos!$B$12) -> 381.98296 | F9: =IF(A9>=Supuestos!$B$15,D9*(1-Supuestos!$B$10)/1000*Supuestos!$B$14,0) -> 4.9112095 | G9: =E9+F9 -> 386.89417 | H9: =G9*Supuestos!$B$19 -> 7350.9893 | I9: 1 | J9: =I9*Supuestos!$B$17 -> 6000 | K9: =H9+J9 -> 13350.989 | L9: =H9*Supuestos!$B$20 -> 294.03957 | M9: =K9*Supuestos!$B$21 -> 200.26484 | N9: =Supuestos!$B$22 -> 500 | O9: =K9-L9-M9-N9 -> 12356.685
A10: 6 | B10: =ROUND(Supuestos!$B$5*Supuestos!$B$6*52/12,0) -> 104 | C10: =Supuestos!$B$7*(1+Supuestos!$B$8)^(A10-1) -> 6034.0716 | D10: =B10*C10 -> 627543.44 | E10: =MIN(D10*Supuestos!$B$10/1000*Supuestos!$B$11,Supuestos!$B$12) -> 439.28041 | F10: =IF(A10>=Supuestos!$B$15,D10*(1-Supuestos!$B$10)/1000*Supuestos!$B$14,0) -> 5.647891 | G10: =E10+F10 -> 444.9283 | H10: =G10*Supuestos!$B$19 -> 8453.6377 | I10: 2 | J10: =I10*Supuestos!$B$17 -> 12000 | K10: =H10+J10 -> 20453.638 | L10: =H10*Supuestos!$B$20 -> 338.14551 | M10: =K10*Supuestos!$B$21 -> 306.80457 | N10: =Supuestos!$B$22 -> 500 | O10: =K10-L10-M10-N10 -> 19308.688
A11: 7 | B11: =ROUND(Supuestos!$B$5*Supuestos!$B$6*52/12,0) -> 104 | C11: =Supuestos!$B$7*(1+Supuestos!$B$8)^(A11-1) -> 6939.1823 | D11: =B11*C11 -> 721674.96 | E11: =MIN(D11*Supuestos!$B$10/1000*Supuestos!$B$11,Supuestos!$B$12) -> 505.17247 | F11: =IF(A11>=Supuestos!$B$15,D11*(1-Supuestos!$B$10)/1000*Supuestos!$B$14,0) -> 6.4950746 | G11: =E11+F11 -> 511.66755 | H11: =G11*Supuestos!$B$19 -> 9721.6834 | I11: 2 | J11: =I11*Supuestos!$B$17 -> 12000 | K11: =H11+J11 -> 21721.683 | L11: =H11*Supuestos!$B$20 -> 388.86733 | M11: =K11*Supuestos!$B$21 -> 325.82525 | N11: =Supuestos!$B$22 -> 500 | O11: =K11-L11-M11-N11 -> 20506.991
A12: 8 | B12: =ROUND(Supuestos!$B$5*Supuestos!$B$6*52/12,0) -> 104 | C12: =Supuestos!$B$7*(1+Supuestos!$B$8)^(A12-1) -> 7980.0596 | D12: =B12*C12 -> 829926.2 | E12: =MIN(D12*Supuestos!$B$10/1000*Supuestos!$B$11,Supuestos!$B$12) -> 580.94834 | F12: =IF(A12>=Supuestos!$B$15,D12*(1-Supuestos!$B$10)/1000*Supuestos!$B$14,0) -> 7.4693358 | G12: =E12+F12 -> 588.41768 | H12: =G12*Supuestos!$B$19 -> 11179.936 | I12: 2 | J12: =I12*Supuestos!$B$17 -> 12000 | K12: =H12+J12 -> 23179.936 | L12: =H12*Supuestos!$B$20 -> 447.19744 | M12: =K12*Supuestos!$B$21 -> 347.69904 | N12: =Supuestos!$B$22 -> 500 | O12: =K12-L12-M12-N12 -> 21885.039
A13: 9 | B13: =ROUND(Supuestos!$B$5*Supuestos!$B$6*52/12,0) -> 104 | C13: =Supuestos!$B$7*(1+Supuestos!$B$8)^(A13-1) -> 9177.0686 | D13: =B13*C13 -> 954415.13 | E13: =MIN(D13*Supuestos!$B$10/1000*Supuestos!$B$11,Supuestos!$B$12) -> 668.09059 | F13: =IF(A13>=Supuestos!$B$15,D13*(1-Supuestos!$B$10)/1000*Supuestos!$B$14,0) -> 8.5897362 | G13: =E13+F13 -> 676.68033 | H13: =G13*Supuestos!$B$19 -> 12856.926 | I13: 2 | J13: =I13*Supuestos!$B$17 -> 12000 | K13: =H13+J13 -> 24856.926 | L13: =H13*Supuestos!$B$20 -> 514.27705 | M13: =K13*Supuestos!$B$21 -> 372.85389 | N13: =Supuestos!$B$22 -> 500 | O13: =K13-L13-M13-N13 -> 23469.795
A14: 10 | B14: =ROUND(Supuestos!$B$5*Supuestos!$B$6*52/12,0) -> 104 | C14: =Supuestos!$B$7*(1+Supuestos!$B$8)^(A14-1) -> 10553.629 | D14: =B14*C14 -> 1097577.4 | E14: =MIN(D14*Supuestos!$B$10/1000*Supuestos!$B$11,Supuestos!$B$12) -> 768.30418 | F14: =IF(A14>=Supuestos!$B$15,D14*(1-Supuestos!$B$10)/1000*Supuestos!$B$14,0) -> 9.8781966 | G14: =E14+F14 -> 778.18238 | H14: =G14*Supuestos!$B$19 -> 14785.465 | I14: 3 | J14: =I14*Supuestos!$B$17 -> 18000 | K14: =H14+J14 -> 32785.465 | L14: =H14*Supuestos!$B$20 -> 591.41861 | M14: =K14*Supuestos!$B$21 -> 491.78198 | N14: =Supuestos!$B$22 -> 500 | O14: =K14-L14-M14-N14 -> 31202.265
A15: 11 | B15: =ROUND(Supuestos!$B$5*Supuestos!$B$6*52/12,0) -> 104 | C15: =Supuestos!$B$7*(1+Supuestos!$B$8)^(A15-1) -> 12136.673 | D15: =B15*C15 -> 1262214 | E15: =MIN(D15*Supuestos!$B$10/1000*Supuestos!$B$11,Supuestos!$B$12) -> 883.54981 | F15: =IF(A15>=Supuestos!$B$15,D15*(1-Supuestos!$B$10)/1000*Supuestos!$B$14,0) -> 11.359926 | G15: =E15+F15 -> 894.90974 | H15: =G15*Supuestos!$B$19 -> 17003.285 | I15: 3 | J15: =I15*Supuestos!$B$17 -> 18000 | K15: =H15+J15 -> 35003.285 | L15: =H15*Supuestos!$B$20 -> 680.1314 | M15: =K15*Supuestos!$B$21 -> 525.04927 | N15: =Supuestos!$B$22 -> 500 | O15: =K15-L15-M15-N15 -> 33298.104
A16: 12 | B16: =ROUND(Supuestos!$B$5*Supuestos!$B$6*52/12,0) -> 104 | C16: =Supuestos!$B$7*(1+Supuestos!$B$8)^(A16-1) -> 13957.174 | D16: =B16*C16 -> 1451546.1 | E16: =MIN(D16*Supuestos!$B$10/1000*Supuestos!$B$11,Supuestos!$B$12) -> 1016.0823 | F16: =IF(A16>=Supuestos!$B$15,D16*(1-Supuestos!$B$10)/1000*Supuestos!$B$14,0) -> 13.063915 | G16: =E16+F16 -> 1029.1462 | H16: =G16*Supuestos!$B$19 -> 19553.778 | I16: 3 | J16: =I16*Supuestos!$B$17 -> 18000 | K16: =H16+J16 -> 37553.778 | L16: =H16*Supuestos!$B$20 -> 782.15111 | M16: =K16*Supuestos!$B$21 -> 563.30667 | N16: =Supuestos!$B$22 -> 500 | O16: =K16-L16-M16-N16 -> 35708.32
A17: Total | B17: =SUM(B5:B16) -> 1248 | D17: =SUM(D5:D16) -> 9048520.2 | E17: =SUM(E5:E16) -> 6333.9642 | F17: =SUM(F5:F16) -> 67.415285 | G17: =SUM(G5:G16) -> 6401.3794 | H17: =SUM(H5:H16) -> 121626.21 | J17: =SUM(J5:J16) -> 120000 | K17: =SUM(K5:K16) -> 241626.21 | L17: =SUM(L5:L16) -> 4865.0484 | M17: =SUM(M5:M16) -> 3624.3931 | N17: =SUM(N5:N16) -> 6000 | O17: =SUM(O5:O16) -> 227136.77
